fungeit/__init__.py
fungeit-0.42.10.dist-info/LICENSE
fungeit-0.42.10.dist-info/WHEEL
fungeit-0.42.10.dist-info/METADATA
fungeit-0.42.10.dist-info/RECORD
